{"context":{"loaders":[{"path":"D:\\account-system-sdk\\node_modules\\babel-loader\\lib\\index.js","query":"?presets=latest"}],"external":{}},"mtimes":{"D:\\account-system-sdk\\src\\js\\register\\init.js":{"mtime":1523282884665,"compiledPath":"D:\\account-system-sdk\\.happypack\\s-1580904580","error":null},"D:\\account-system-sdk\\src\\js\\index.js":{"mtime":1523282884661,"compiledPath":"D:\\account-system-sdk\\.happypack\\s--1485488652","error":null},"D:\\account-system-sdk\\src\\js\\register\\info\\init.js":{"mtime":1523282884664,"compiledPath":"D:\\account-system-sdk\\.happypack\\s--933262382","error":null},"D:\\account-system-sdk\\src\\js\\forget\\init.js":{"mtime":1523282884661,"compiledPath":"D:\\account-system-sdk\\.happypack\\s-1847936036","error":null},"D:\\account-system-sdk\\src\\js\\register\\mobile\\init.js":{"mtime":1523282884667,"compiledPath":"D:\\account-system-sdk\\.happypack\\s-1709232663","error":null},"D:\\account-system-sdk\\src\\js\\delivery-address\\init.js":{"mtime":1523282884658,"compiledPath":"D:\\account-system-sdk\\.happypack\\s--267849139","error":null},"D:\\account-system-sdk\\src\\js\\register\\payment\\init.js":{"mtime":1523282884668,"compiledPath":"D:\\account-system-sdk\\.happypack\\s-853365679","error":null},"D:\\account-system-sdk\\src\\js\\forget\\render.js":{"mtime":1523282884661,"compiledPath":"D:\\account-system-sdk\\.happypack\\s-1109852627","error":null},"D:\\account-system-sdk\\src\\js\\common\\fetch.js":{"mtime":1523282884653,"compiledPath":"D:\\account-system-sdk\\.happypack\\s-101100507","error":null},"D:\\account-system-sdk\\src\\js\\login\\render.js":{"mtime":1523282884663,"compiledPath":"D:\\account-system-sdk\\.happypack\\s--623238904","error":null},"D:\\account-system-sdk\\src\\js\\common\\polyfill.js":{"mtime":1523282884655,"compiledPath":"D:\\account-system-sdk\\.happypack\\s--204735198","error":null},"D:\\account-system-sdk\\src\\js\\login\\event.js":{"mtime":1523282884662,"compiledPath":"D:\\account-system-sdk\\.happypack\\s--249204105","error":null},"D:\\account-system-sdk\\src\\js\\register\\info\\render.js":{"mtime":1523282884665,"compiledPath":"D:\\account-system-sdk\\.happypack\\s--1626499175","error":null},"D:\\account-system-sdk\\src\\js\\delivery-address\\render.js":{"mtime":1523282884659,"compiledPath":"D:\\account-system-sdk\\.happypack\\s--1442854575","error":null},"D:\\account-system-sdk\\src\\js\\register\\mobile\\render.js":{"mtime":1523282884667,"compiledPath":"D:\\account-system-sdk\\.happypack\\s-1189397106","error":null},"D:\\account-system-sdk\\src\\js\\register\\info\\event.js":{"mtime":1523282884664,"compiledPath":"D:\\account-system-sdk\\.happypack\\s--1428251283","error":null},"D:\\account-system-sdk\\src\\js\\register\\mobile\\event.js":{"mtime":1523282884666,"compiledPath":"D:\\account-system-sdk\\.happypack\\s-1004085140","error":null},"D:\\account-system-sdk\\src\\js\\register\\payment\\render.js":{"mtime":1523282884669,"compiledPath":"D:\\account-system-sdk\\.happypack\\s--426982468","error":null},"D:\\account-system-sdk\\src\\js\\forget\\event.js":{"mtime":1523282884659,"compiledPath":"D:\\account-system-sdk\\.happypack\\s--457635543","error":null},"D:\\account-system-sdk\\src\\js\\register\\payment\\event.js":{"mtime":1523282884668,"compiledPath":"D:\\account-system-sdk\\.happypack\\s-186400889","error":null},"D:\\account-system-sdk\\src\\js\\delivery-address\\event.js":{"mtime":1523282884658,"compiledPath":"D:\\account-system-sdk\\.happypack\\s--1287968166","error":null},"D:\\account-system-sdk\\src\\js\\common\\from-check.js":{"mtime":1523282884654,"compiledPath":"D:\\account-system-sdk\\.happypack\\s--244015858","error":null},"D:\\account-system-sdk\\src\\js\\common\\utils.js":{"mtime":1523282884657,"compiledPath":"D:\\account-system-sdk\\.happypack\\s--940908827","error":null},"D:\\account-system-sdk\\src\\js\\common\\slider.js":{"mtime":1523282884656,"compiledPath":"D:\\account-system-sdk\\.happypack\\s-7065025","error":null},"D:\\account-system-sdk\\src\\js\\common\\mock.js":{"mtime":1523282884655,"compiledPath":"D:\\account-system-sdk\\.happypack\\s-1003499534","error":null},"D:\\account-system-sdk\\src\\js\\common\\region.js":{"mtime":1523282884656,"compiledPath":"D:\\account-system-sdk\\.happypack\\s-1454773182","error":null},"D:\\account-system-sdk\\src\\js\\forget\\findTpl.js":{"mtime":1523282884660,"compiledPath":"D:\\account-system-sdk\\.happypack\\s--1365208554","error":null},"D:\\account-system-sdk\\src\\js\\security\\init.js":{"mtime":1523282884670,"compiledPath":"D:\\account-system-sdk\\.happypack\\s-389482649","error":null},"D:\\account-system-sdk\\src\\js\\security\\render.js":{"mtime":1523282884670,"compiledPath":"D:\\account-system-sdk\\.happypack\\s--1553726542","error":null},"D:\\account-system-sdk\\src\\js\\common\\data\\region-data.js":{"mtime":1523282884653,"compiledPath":"D:\\account-system-sdk\\.happypack\\s--880203949","error":null},"D:\\account-system-sdk\\src\\js\\login\\init.js":{"mtime":1523283770396,"compiledPath":"D:\\account-system-sdk\\.happypack\\s-630942938","error":null}}}